{"-8": {"economic_activity_status_4a": {"count": [0, 0, 0], "percent": [null, null, null]}, "english_proficiency": {"count": [0, 0, 0, 0, 0], "percent": [null, null, null, null, null]}, "ethnic_group_tb_6a": {"count": [0, 0, 0, 0, 0], "percent": [null, null, null, null, null]}, "has_ever_worked": {"count": [0, 0, 0], "percent": [null, null, null]}, "health_in_general": {"count": [0, 0, 0, 0, 0], "percent": [null, null, null, null, null]}, "highest_qualification": {"count": [0, 0, 0, 0, 0], "percent": [null, null, null, null, null]}, "hours_per_week_worked": {"count": [0, 0, 0, 0], "percent": [null, null, null, null]}, "is_carer_5a": {"count": [0, 0, 0, 0], "percent": [null, null, null, null]}, "legal_partnership_status_6a": {"count": [0, 0, 0, 0, 0], "percent": [null, null, null, null, null]}, "ns_sec_10a": {"count": [0, 0, 0, 0, 0, 0, 0, 0, 0], "percent": [null, null, null, null, null, null, null, null, null]}, "occupation_current_10a": {"count": [0, 0, 0, 0, 0, 0, 0, 0, 0], "percent": [null, null, null, null, null, null, null, null, null]}, "passports_all_4a": {"count": [0, 0, 0], "percent": [null, null, null]}, "religion_tb": {"count": [0, 0, 0, 0, 0, 0, 0, 0, 0], "percent": [null, null, null, null, null, null, null, null, null]}, "residence_length_6b": {"count": [0, 0, 0, 0, 0], "percent": [null, null, null, null, null]}, "resident_age_18b": {"count": [0, 0, 0, 0, 0, 0, 0, 0, 0, 0, 0, 0, 0, 0, 0, 0, 0, 0], "percent": [null, null, null, null, null, null, null, null, null, null, null, null, null, null, null, null, null, null]}, "sex": {"count": [0, 0], "percent": [null, null]}, "transport_to_workplace_12a": {"count": [0, 0, 0, 0, 0, 0, 0, 0, 0, 0, 0], "percent": [null, null, null, null, null, null, null, null, null, null, null]}, "workplace_travel_8a": {"count": [0, 0, 0, 0, 0], "percent": [null, null, null, null, null]}, "total_pop": {"count": 0, "percent": 0.0}}, "1": {"economic_activity_status_4a": {"count": [387773, 45425, 3216026], "percent": [10.6, 1.2, 88.1]}, "english_proficiency": {"count": [3881581, 4315, 3077, 5876, 7674], "percent": [99.5, 0.1, 0.1, 0.2, 0.2]}, "ethnic_group_tb_6a": {"count": [79610, 51987, 70044, 3699550, 13440], "percent": [2.0, 1.3, 1.8, 94.5, 0.3]}, "has_ever_worked": {"count": [92783, 2248214, 920455], "percent": [2.8, 68.9, 28.2]}, "health_in_general": {"count": [138610, 438912, 1317984, 1466209, 552915], "percent": [3.5, 11.2, 33.7, 37.5, 14.1]}, "highest_qualification": {"count": [1482288, 1204602, 244736, 570199, 147399], "percent": [40.6, 33.0, 6.7, 15.6, 4.0]}, "hours_per_week_worked": {"count": [89085, 107828, 161214, 29646], "percent": [23.0, 27.8, 41.6, 7.6]}, "is_carer_5a": {"count": [3457732, 126169, 93494, 201051], "percent": [89.2, 3.3, 2.4, 5.2]}, "legal_partnership_status_6a": {"count": [1140275, 1273584, 108306, 513281, 613776], "percent": [31.2, 34.9, 3.0, 14.1, 16.8]}, "ns_sec_10a": {"count": [182787, 462415, 369430, 309337, 206570, 538049, 601403, 856665, 122568], "percent": [5.0, 12.7, 10.1, 8.5, 5.7, 14.7, 16.5, 23.5, 3.4]}, "occupation_current_10a": {"count": [39003, 50599, 47588, 47250, 37226, 48881, 43463, 26137, 47627], "percent": [10.1, 13.0, 12.3, 12.2, 9.6, 12.6, 11.2, 6.7, 12.3]}, "passports_all_4a": {"count": [2584570, 6719, 1323341], "percent": [66.0, 0.2, 33.8]}, "religion_tb": {"count": [1303393, 2192059, 11289, 7341, 14118, 69758, 8377, 38144, 270151], "percent": [33.3, 56.0, 0.3, 0.2, 0.4, 1.8, 0.2, 1.0, 6.9]}, "residence_length_6b": {"count": [3914630, 0, 0, 0, 0], "percent": [100.0, 0.0, 0.0, 0.0, 0.0]}, "resident_age_18b": {"count": [36184, 92585, 112818, 124536, 131269, 130623, 138378, 145795, 159938, 209262, 284406, 330008, 333536, 292385, 320547, 304644, 296478, 471238], "percent": [0.9, 2.4, 2.9, 3.2, 3.4, 3.3, 3.5, 3.7, 4.1, 5.3, 7.3, 8.4, 8.5, 7.5, 8.2, 7.8, 7.6, 12.0]}, "sex": {"count": [2140552, 1774078], "percent": [54.7, 45.3]}, "transport_to_workplace_12a": {"count": [125885, 2676, 4770, 18967, 7323, 1857, 158514, 22995, 5321, 28639, 10826], "percent": [32.5, 0.7, 1.2, 4.9, 1.9, 0.5, 40.9, 5.9, 1.4, 7.4, 2.8]}, "workplace_travel_8a": {"count": [139393, 47605, 13297, 125885, 61593], "percent": [35.9, 12.3, 3.4, 32.5, 15.9]}, "total_pop": {"count": 3914630, "percent": 6.6}}, "2": {"economic_activity_status_4a": {"count": [4449, 648, 13776], "percent": [23.6, 3.4, 73.0]}, "english_proficiency": {"count": [20994, 353, 177, 191, 184], "percent": [95.9, 1.6, 0.8, 0.9, 0.8]}, "ethnic_group_tb_6a": {"count": [2461, 1026, 2170, 15570, 864], "percent": [11.1, 4.6, 9.8, 70.5, 3.9]}, "has_ever_worked": {"count": [1057, 9787, 3581], "percent": [7.3, 67.8, 24.8]}, "health_in_general": {"count": [1488, 3586, 7023, 7310, 2683], "percent": [6.7, 16.2, 31.8, 33.1, 12.1]}, "highest_qualification": {"count": [2431, 7414, 559, 8099, 371], "percent": [12.9, 39.3, 3.0, 42.9, 2.0]}, "hours_per_week_worked": {"count": [1129, 1056, 1858, 406], "percent": [25.4, 23.7, 41.8, 9.1]}, "is_carer_5a": {"count": [18086, 1749, 656, 1060], "percent": [83.9, 8.1, 3.0, 4.9]}, "legal_partnership_status_6a": {"count": [9977, 4998, 548, 2379, 972], "percent": [52.9, 26.5, 2.9, 12.6, 5.1]}, "ns_sec_10a": {"count": [2306, 4133, 2019, 1526, 627, 1836, 1520, 2864, 2043], "percent": [12.2, 21.9, 10.7, 8.1, 3.3, 9.7, 8.1, 15.2, 10.8]}, "occupation_current_10a": {"count": [446, 1312, 948, 411, 214, 351, 367, 136, 264], "percent": [10.0, 29.5, 21.3, 9.2, 4.8, 7.9, 8.2, 3.1, 5.9]}, "passports_all_4a": {"count": [18231, 1045, 2815], "percent": [82.5, 4.7, 12.7]}, "religion_tb": {"count": [8838, 7502, 257, 399, 163, 1911, 286, 1056, 1679], "percent": [40.0, 34.0, 1.2, 1.8, 0.7, 8.7, 1.3, 4.8, 7.6]}, "residence_length_6b": {"count": [22091, 0, 0, 0, 0], "percent": [100.0, 0.0, 0.0, 0.0, 0.0]}, "resident_age_18b": {"count": [543, 1189, 1223, 1492, 1653, 1420, 1388, 1395, 1467, 1633, 1838, 1925, 1510, 1037, 844, 524, 424, 586], "percent": [2.5, 5.4, 5.5, 6.8, 7.5, 6.4, 6.3, 6.3, 6.6, 7.4, 8.3, 8.7, 6.8, 4.7, 3.8, 2.4, 1.9, 2.7]}, "sex": {"count": [11578, 10513], "percent": [52.4, 47.6]}, "transport_to_workplace_12a": {"count": [2445, 87, 98, 195, 63, 17, 982, 154, 86, 225, 97], "percent": [55.0, 2.0, 2.2, 4.4, 1.4, 0.4, 22.1, 3.5, 1.9, 5.1, 2.2]}, "workplace_travel_8a": {"count": [1035, 399, 143, 2445, 428], "percent": [23.3, 9.0, 3.2, 54.9, 9.6]}, "total_pop": {"count": 22091, "percent": 0.0}}, "3": {"economic_activity_status_4a": {"count": [4976, 605, 15754], "percent": [23.3, 2.8, 73.8]}, "english_proficiency": {"count": [23040, 546, 436, 672, 514], "percent": [91.4, 2.2, 1.7, 2.7, 2.0]}, "ethnic_group_tb_6a": {"count": [1783, 1361, 1674, 19314, 1417], "percent": [7.0, 5.3, 6.6, 75.6, 5.5]}, "has_ever_worked": {"count": [983, 10909, 4468], "percent": [6.0, 66.7, 27.3]}, "health_in_general": {"count": [1667, 3867, 7912, 8620, 3484], "percent": [6.5, 15.1, 31.0, 33.7, 13.6]}, "highest_qualification": {"count": [4173, 7413, 736, 8519, 496], "percent": [19.6, 34.7, 3.4, 39.9, 2.3]}, "hours_per_week_worked": {"count": [1119, 1222, 2081, 553], "percent": [22.5, 24.6, 41.8, 11.1]}, "is_carer_5a": {"count": [20958, 1679, 721, 1245], "percent": [85.2, 6.8, 2.9, 5.1]}, "legal_partnership_status_6a": {"count": [9661, 6243, 734, 3176, 1522], "percent": [45.3, 29.3, 3.4, 14.9, 7.1]}, "ns_sec_10a": {"count": [2395, 4592, 2062, 2098, 812, 2033, 1893, 3917, 1537], "percent": [11.2, 21.5, 9.7, 9.8, 3.8, 9.5, 8.9, 18.4, 7.2]}, "occupation_current_10a": {"count": [593, 1305, 973, 512, 300, 424, 369, 172, 328], "percent": [11.9, 26.2, 19.6, 10.3, 6.0, 8.5, 7.4, 3.5, 6.6]}, "passports_all_4a": {"count": [15434, 5502, 4614], "percent": [60.4, 21.5, 18.1]}, "religion_tb": {"count": [10446, 8885, 377, 319, 144, 1844, 206, 1170, 2155], "percent": [40.9, 34.8, 1.5, 1.2, 0.6, 7.2, 0.8, 4.6, 8.4]}, "residence_length_6b": {"count": [25550, 0, 0, 0, 0], "percent": [100.0, 0.0, 0.0, 0.0, 0.0]}, "resident_age_18b": {"count": [947, 1721, 1284, 1150, 1167, 1171, 1160, 1261, 1406, 1795, 2443, 2777, 2357, 1577, 1096, 739, 618, 881], "percent": [3.7, 6.7, 5.0, 4.5, 4.6, 4.6, 4.5, 4.9, 5.5, 7.0, 9.6, 10.9, 9.2, 6.2, 4.3, 2.9, 2.4, 3.4]}, "sex": {"count": [12306, 13244], "percent": [48.2, 51.8]}, "transport_to_workplace_12a": {"count": [2592, 87, 91, 228, 58, 23, 1178, 132, 117, 308, 159], "percent": [52.1, 1.7, 1.8, 4.6, 1.2, 0.5, 23.7, 2.7, 2.4, 6.2, 3.2]}, "workplace_travel_8a": {"count": [1135, 470, 174, 2592, 606], "percent": [22.8, 9.4, 3.5, 52.1, 12.2]}, "total_pop": {"count": 25550, "percent": 0.0}}}