{"1": {"country_of_birth_3a": {"count": [6020, 10589], "percent": [36.2, 63.8]}, "disability_3a": "blocked", "economic_activity_status_4a": "blocked", "english_proficiency": "blocked", "has_ever_worked": "blocked", "health_in_general": "blocked", "highest_qualification": "blocked", "hours_per_week_worked": "blocked", "is_carer_5a": "blocked", "legal_partnership_status_6a": "blocked", "national_identity_all_4a": "blocked", "ns_sec_10a": "blocked", "occupation_current_10a": "blocked", "religion_tb": "blocked", "residence_length_6b": "blocked", "resident_age_18b": {"count": [16609, 19850, 11852, 9746, 27834, 42923, 68101, 60220, 32774, 16756, 9763, 7340, 6170, 5471, 4529, 3331, 2815, 2508], "percent": [4.8, 5.7, 3.4, 2.8, 8.0, 12.3, 19.5, 17.3, 9.4, 4.8, 2.8, 2.1, 1.8, 1.6, 1.3, 1.0, 0.8, 0.7]}, "sex": {"count": [8219, 8390], "percent": [49.5, 50.5]}, "transport_to_workplace_12a": "blocked", "workplace_travel_8a": "blocked", "total_pop": {"count": 16609, "percent": 0.0}}, "2": {"country_of_birth_3a": {"count": [2656, 17194], "percent": [13.4, 86.6]}, "disability_3a": "blocked", "economic_activity_status_4a": "blocked", "english_proficiency": "blocked", "has_ever_worked": "blocked", "health_in_general": "blocked", "highest_qualification": "blocked", "hours_per_week_worked": "blocked", "is_carer_5a": "blocked", "legal_partnership_status_6a": "blocked", "national_identity_all_4a": "blocked", "ns_sec_10a": "blocked", "occupation_current_10a": "blocked", "religion_tb": "blocked", "residence_length_6b": "blocked", "resident_age_18b": {"count": [16609, 19850, 11852, 9746, 27834, 42923, 68101, 60220, 32774, 16756, 9763, 7340, 6170, 5471, 4529, 3331, 2815, 2508], "percent": [4.8, 5.7, 3.4, 2.8, 8.0, 12.3, 19.5, 17.3, 9.4, 4.8, 2.8, 2.1, 1.8, 1.6, 1.3, 1.0, 0.8, 0.7]}, "sex": {"count": [9780, 10070], "percent": [49.3, 50.7]}, "transport_to_workplace_12a": "blocked", "workplace_travel_8a": "blocked", "total_pop": {"count": 19850, "percent": 0.0}}, "3": {"country_of_birth_3a": {"count": [775, 11077], "percent": [6.5, 93.5]}, "disability_3a": "blocked", "economic_activity_status_4a": "blocked", "english_proficiency": "blocked", "has_ever_worked": "blocked", "health_in_general": "blocked", "highest_qualification": "blocked", "hours_per_week_worked": "blocked", "is_carer_5a": "blocked", "legal_partnership_status_6a": "blocked", "national_identity_all_4a": "blocked", "ns_sec_10a": "blocked", "occupation_current_10a": "blocked", "religion_tb": "blocked", "residence_length_6b": "blocked", "resident_age_18b": {"count": [16609, 19850, 11852, 9746, 27834, 42923, 68101, 60220, 32774, 16756, 9763, 7340, 6170, 5471, 4529, 3331, 2815, 2508], "percent": [4.8, 5.7, 3.4, 2.8, 8.0, 12.3, 19.5, 17.3, 9.4, 4.8, 2.8, 2.1, 1.8, 1.6, 1.3, 1.0, 0.8, 0.7]}, "sex": {"count": [5726, 6126], "percent": [48.3, 51.7]}, "transport_to_workplace_12a": "blocked", "workplace_travel_8a": "blocked", "total_pop": {"count": 11852, "percent": 0.0}}, "4": {"country_of_birth_3a": {"count": [229, 9517], "percent": [2.3, 97.7]}, "disability_3a": "blocked", "economic_activity_status_4a": "blocked", "english_proficiency": "blocked", "has_ever_worked": "blocked", "health_in_general": "blocked", "highest_qualification": "blocked", "hours_per_week_worked": "blocked", "is_carer_5a": "blocked", "legal_partnership_status_6a": "blocked", "national_identity_all_4a": "blocked", "ns_sec_10a": "blocked", "occupation_current_10a": "blocked", "religion_tb": "blocked", "residence_length_6b": "blocked", "resident_age_18b": {"count": [16609, 19850, 11852, 9746, 27834, 42923, 68101, 60220, 32774, 16756, 9763, 7340, 6170, 5471, 4529, 3331, 2815, 2508], "percent": [4.8, 5.7, 3.4, 2.8, 8.0, 12.3, 19.5, 17.3, 9.4, 4.8, 2.8, 2.1, 1.8, 1.6, 1.3, 1.0, 0.8, 0.7]}, "sex": {"count": [4705, 5041], "percent": [48.3, 51.7]}, "transport_to_workplace_12a": "blocked", "workplace_travel_8a": "blocked", "total_pop": {"count": 9746, "percent": 0.0}}, "5": {"country_of_birth_3a": {"count": [348, 27486], "percent": [1.3, 98.7]}, "disability_3a": "blocked", "economic_activity_status_4a": "blocked", "english_proficiency": "blocked", "has_ever_worked": "blocked", "health_in_general": "blocked", "highest_qualification": "blocked", "hours_per_week_worked": "blocked", "is_carer_5a": "blocked", "legal_partnership_status_6a": "blocked", "national_identity_all_4a": "blocked", "ns_sec_10a": "blocked", "occupation_current_10a": "blocked", "religion_tb": "blocked", "residence_length_6b": "blocked", "resident_age_18b": {"count": [16609, 19850, 11852, 9746, 27834, 42923, 68101, 60220, 32774, 16756, 9763, 7340, 6170, 5471, 4529, 3331, 2815, 2508], "percent": [4.8, 5.7, 3.4, 2.8, 8.0, 12.3, 19.5, 17.3, 9.4, 4.8, 2.8, 2.1, 1.8, 1.6, 1.3, 1.0, 0.8, 0.7]}, "sex": {"count": [11700, 16136], "percent": [42.0, 58.0]}, "transport_to_workplace_12a": "blocked", "workplace_travel_8a": "blocked", "total_pop": {"count": 27834, "percent": 0.0}}, "6": {"country_of_birth_3a": {"count": [377, 42546], "percent": [0.9, 99.1]}, "disability_3a": "blocked", "economic_activity_status_4a": "blocked", "english_proficiency": "blocked", "has_ever_worked": "blocked", "health_in_general": "blocked", "highest_qualification": "blocked", "hours_per_week_worked": "blocked", "is_carer_5a": "blocked", "legal_partnership_status_6a": "blocked", "national_identity_all_4a": "blocked", "ns_sec_10a": "blocked", "occupation_current_10a": "blocked", "religion_tb": "blocked", "residence_length_6b": "blocked", "resident_age_18b": {"count": [16609, 19850, 11852, 9746, 27834, 42923, 68101, 60220, 32774, 16756, 9763, 7340, 6170, 5471, 4529, 3331, 2815, 2508], "percent": [4.8, 5.7, 3.4, 2.8, 8.0, 12.3, 19.5, 17.3, 9.4, 4.8, 2.8, 2.1, 1.8, 1.6, 1.3, 1.0, 0.8, 0.7]}, "sex": {"count": [23947, 18973], "percent": [55.8, 44.2]}, "transport_to_workplace_12a": "blocked", "workplace_travel_8a": "blocked", "total_pop": {"count": 42923, "percent": 0.1}}, "7": {"country_of_birth_3a": {"count": [383, 67718], "percent": [0.6, 99.4]}, "disability_3a": "blocked", "economic_activity_status_4a": "blocked", "english_proficiency": "blocked", "has_ever_worked": "blocked", "health_in_general": "blocked", "highest_qualification": "blocked", "hours_per_week_worked": "blocked", "is_carer_5a": "blocked", "legal_partnership_status_6a": "blocked", "national_identity_all_4a": "blocked", "ns_sec_10a": "blocked", "occupation_current_10a": "blocked", "religion_tb": "blocked", "residence_length_6b": "blocked", "resident_age_18b": {"count": [16609, 19850, 11852, 9746, 27834, 42923, 68101, 60220, 32774, 16756, 9763, 7340, 6170, 5471, 4529, 3331, 2815, 2508], "percent": [4.8, 5.7, 3.4, 2.8, 8.0, 12.3, 19.5, 17.3, 9.4, 4.8, 2.8, 2.1, 1.8, 1.6, 1.3, 1.0, 0.8, 0.7]}, "sex": {"count": [37954, 30147], "percent": [55.7, 44.3]}, "transport_to_workplace_12a": "blocked", "workplace_travel_8a": "blocked", "total_pop": {"count": 68101, "percent": 0.1}}, "8": {"country_of_birth_3a": {"count": [339, 59881], "percent": [0.6, 99.4]}, "disability_3a": "blocked", "economic_activity_status_4a": "blocked", "english_proficiency": "blocked", "has_ever_worked": "blocked", "health_in_general": "blocked", "highest_qualification": "blocked", "hours_per_week_worked": "blocked", "is_carer_5a": "blocked", "legal_partnership_status_6a": "blocked", "national_identity_all_4a": "blocked", "ns_sec_10a": "blocked", "occupation_current_10a": "blocked", "religion_tb": "blocked", "residence_length_6b": "blocked", "resident_age_18b": {"count": [16609, 19850, 11852, 9746, 27834, 42923, 68101, 60220, 32774, 16756, 9763, 7340, 6170, 5471, 4529, 3331, 2815, 2508], "percent": [4.8, 5.7, 3.4, 2.8, 8.0, 12.3, 19.5, 17.3, 9.4, 4.8, 2.8, 2.1, 1.8, 1.6, 1.3, 1.0, 0.8, 0.7]}, "sex": {"count": [29404, 30816], "percent": [48.8, 51.2]}, "transport_to_workplace_12a": "blocked", "workplace_travel_8a": "blocked", "total_pop": {"count": 60220, "percent": 0.1}}, "9": {"country_of_birth_3a": {"count": [186, 32588], "percent": [0.6, 99.4]}, "disability_3a": "blocked", "economic_activity_status_4a": "blocked", "english_proficiency": "blocked", "has_ever_worked": "blocked", "health_in_general": "blocked", "highest_qualification": "blocked", "hours_per_week_worked": "blocked", "is_carer_5a": "blocked", "legal_partnership_status_6a": "blocked", "national_identity_all_4a": "blocked", "ns_sec_10a": "blocked", "occupation_current_10a": "blocked", "religion_tb": "blocked", "residence_length_6b": "blocked", "resident_age_18b": {"count": [16609, 19850, 11852, 9746, 27834, 42923, 68101, 60220, 32774, 16756, 9763, 7340, 6170, 5471, 4529, 3331, 2815, 2508], "percent": [4.8, 5.7, 3.4, 2.8, 8.0, 12.3, 19.5, 17.3, 9.4, 4.8, 2.8, 2.1, 1.8, 1.6, 1.3, 1.0, 0.8, 0.7]}, "sex": {"count": [14804, 17970], "percent": [45.2, 54.8]}, "transport_to_workplace_12a": "blocked", "workplace_travel_8a": "blocked", "total_pop": {"count": 32774, "percent": 0.1}}, "10": {"country_of_birth_3a": {"count": [130, 16627], "percent": [0.8, 99.2]}, "disability_3a": "blocked", "economic_activity_status_4a": "blocked", "english_proficiency": "blocked", "has_ever_worked": "blocked", "health_in_general": "blocked", "highest_qualification": "blocked", "hours_per_week_worked": "blocked", "is_carer_5a": "blocked", "legal_partnership_status_6a": "blocked", "national_identity_all_4a": "blocked", "ns_sec_10a": "blocked", "occupation_current_10a": "blocked", "religion_tb": "blocked", "residence_length_6b": "blocked", "resident_age_18b": {"count": [16609, 19850, 11852, 9746, 27834, 42923, 68101, 60220, 32774, 16756, 9763, 7340, 6170, 5471, 4529, 3331, 2815, 2508], "percent": [4.8, 5.7, 3.4, 2.8, 8.0, 12.3, 19.5, 17.3, 9.4, 4.8, 2.8, 2.1, 1.8, 1.6, 1.3, 1.0, 0.8, 0.7]}, "sex": {"count": [7629, 9127], "percent": [45.5, 54.5]}, "transport_to_workplace_12a": "blocked", "workplace_travel_8a": "blocked", "total_pop": {"count": 16756, "percent": 0.0}}, "11": {"country_of_birth_3a": {"count": [114, 9649], "percent": [1.2, 98.8]}, "disability_3a": "blocked", "economic_activity_status_4a": "blocked", "english_proficiency": "blocked", "has_ever_worked": "blocked", "health_in_general": "blocked", "highest_qualification": "blocked", "hours_per_week_worked": "blocked", "is_carer_5a": "blocked", "legal_partnership_status_6a": "blocked", "national_identity_all_4a": "blocked", "ns_sec_10a": "blocked", "occupation_current_10a": "blocked", "religion_tb": "blocked", "residence_length_6b": "blocked", "resident_age_18b": {"count": [16609, 19850, 11852, 9746, 27834, 42923, 68101, 60220, 32774, 16756, 9763, 7340, 6170, 5471, 4529, 3331, 2815, 2508], "percent": [4.8, 5.7, 3.4, 2.8, 8.0, 12.3, 19.5, 17.3, 9.4, 4.8, 2.8, 2.1, 1.8, 1.6, 1.3, 1.0, 0.8, 0.7]}, "sex": {"count": [4870, 4893], "percent": [49.9, 50.1]}, "transport_to_workplace_12a": "blocked", "workplace_travel_8a": "blocked", "total_pop": {"count": 9763, "percent": 0.0}}, "12": {"country_of_birth_3a": {"count": [85, 7252], "percent": [1.2, 98.8]}, "disability_3a": "blocked", "economic_activity_status_4a": "blocked", "english_proficiency": "blocked", "has_ever_worked": "blocked", "health_in_general": "blocked", "highest_qualification": "blocked", "hours_per_week_worked": "blocked", "is_carer_5a": "blocked", "legal_partnership_status_6a": "blocked", "national_identity_all_4a": "blocked", "ns_sec_10a": "blocked", "occupation_current_10a": "blocked", "religion_tb": "blocked", "residence_length_6b": "blocked", "resident_age_18b": {"count": [16609, 19850, 11852, 9746, 27834, 42923, 68101, 60220, 32774, 16756, 9763, 7340, 6170, 5471, 4529, 3331, 2815, 2508], "percent": [4.8, 5.7, 3.4, 2.8, 8.0, 12.3, 19.5, 17.3, 9.4, 4.8, 2.8, 2.1, 1.8, 1.6, 1.3, 1.0, 0.8, 0.7]}, "sex": {"count": [4164, 3173], "percent": [56.8, 43.2]}, "transport_to_workplace_12a": "blocked", "workplace_travel_8a": "blocked", "total_pop": {"count": 7340, "percent": 0.0}}, "13": {"country_of_birth_3a": {"count": [90, 6080], "percent": [1.5, 98.5]}, "disability_3a": "blocked", "economic_activity_status_4a": "blocked", "english_proficiency": "blocked", "has_ever_worked": "blocked", "health_in_general": "blocked", "highest_qualification": "blocked", "hours_per_week_worked": "blocked", "is_carer_5a": "blocked", "legal_partnership_status_6a": "blocked", "national_identity_all_4a": "blocked", "ns_sec_10a": "blocked", "occupation_current_10a": "blocked", "religion_tb": "blocked", "residence_length_6b": "blocked", "resident_age_18b": {"count": [16609, 19850, 11852, 9746, 27834, 42923, 68101, 60220, 32774, 16756, 9763, 7340, 6170, 5471, 4529, 3331, 2815, 2508], "percent": [4.8, 5.7, 3.4, 2.8, 8.0, 12.3, 19.5, 17.3, 9.4, 4.8, 2.8, 2.1, 1.8, 1.6, 1.3, 1.0, 0.8, 0.7]}, "sex": {"count": [3643, 2527], "percent": [59.0, 41.0]}, "transport_to_workplace_12a": "blocked", "workplace_travel_8a": "blocked", "total_pop": {"count": 6170, "percent": 0.0}}, "14": {"country_of_birth_3a": {"count": [68, 5403], "percent": [1.2, 98.8]}, "disability_3a": "blocked", "economic_activity_status_4a": "blocked", "english_proficiency": "blocked", "has_ever_worked": "blocked", "health_in_general": "blocked", "highest_qualification": "blocked", "hours_per_week_worked": "blocked", "is_carer_5a": "blocked", "legal_partnership_status_6a": "blocked", "national_identity_all_4a": "blocked", "ns_sec_10a": "blocked", "occupation_current_10a": "blocked", "religion_tb": "blocked", "residence_length_6b": "blocked", "resident_age_18b": {"count": [16609, 19850, 11852, 9746, 27834, 42923, 68101, 60220, 32774, 16756, 9763, 7340, 6170, 5471, 4529, 3331, 2815, 2508], "percent": [4.8, 5.7, 3.4, 2.8, 8.0, 12.3, 19.5, 17.3, 9.4, 4.8, 2.8, 2.1, 1.8, 1.6, 1.3, 1.0, 0.8, 0.7]}, "sex": {"count": [3418, 2053], "percent": [62.5, 37.5]}, "transport_to_workplace_12a": "blocked", "workplace_travel_8a": "blocked", "total_pop": {"count": 5471, "percent": 0.0}}, "15": {"country_of_birth_3a": {"count": [62, 4467], "percent": [1.4, 98.6]}, "disability_3a": "blocked", "economic_activity_status_4a": "blocked", "english_proficiency": "blocked", "has_ever_worked": "blocked", "health_in_general": "blocked", "highest_qualification": "blocked", "hours_per_week_worked": "blocked", "is_carer_5a": "blocked", "legal_partnership_status_6a": "blocked", "national_identity_all_4a": "blocked", "ns_sec_10a": "blocked", "occupation_current_10a": "blocked", "religion_tb": "blocked", "residence_length_6b": "blocked", "resident_age_18b": {"count": [16609, 19850, 11852, 9746, 27834, 42923, 68101, 60220, 32774, 16756, 9763, 7340, 6170, 5471, 4529, 3331, 2815, 2508], "percent": [4.8, 5.7, 3.4, 2.8, 8.0, 12.3, 19.5, 17.3, 9.4, 4.8, 2.8, 2.1, 1.8, 1.6, 1.3, 1.0, 0.8, 0.7]}, "sex": {"count": [3022, 1507], "percent": [66.7, 33.3]}, "transport_to_workplace_12a": "blocked", "workplace_travel_8a": "blocked", "total_pop": {"count": 4529, "percent": 0.0}}, "16": {"country_of_birth_3a": {"count": [51, 3281], "percent": [1.5, 98.5]}, "disability_3a": "blocked", "economic_activity_status_4a": "blocked", "english_proficiency": "blocked", "has_ever_worked": "blocked", "health_in_general": "blocked", "highest_qualification": "blocked", "hours_per_week_worked": "blocked", "is_carer_5a": "blocked", "legal_partnership_status_6a": "blocked", "national_identity_all_4a": "blocked", "ns_sec_10a": "blocked", "occupation_current_10a": "blocked", "religion_tb": "blocked", "residence_length_6b": "blocked", "resident_age_18b": {"count": [16609, 19850, 11852, 9746, 27834, 42923, 68101, 60220, 32774, 16756, 9763, 7340, 6170, 5471, 4529, 3331, 2815, 2508], "percent": [4.8, 5.7, 3.4, 2.8, 8.0, 12.3, 19.5, 17.3, 9.4, 4.8, 2.8, 2.1, 1.8, 1.6, 1.3, 1.0, 0.8, 0.7]}, "sex": {"count": [2376, 957], "percent": [71.3, 28.7]}, "transport_to_workplace_12a": "blocked", "workplace_travel_8a": "blocked", "total_pop": {"count": 3331, "percent": 0.0}}, "17": {"country_of_birth_3a": {"count": [26, 2789], "percent": [0.9, 99.1]}, "disability_3a": "blocked", "economic_activity_status_4a": "blocked", "english_proficiency": "blocked", "has_ever_worked": "blocked", "health_in_general": "blocked", "highest_qualification": "blocked", "hours_per_week_worked": "blocked", "is_carer_5a": "blocked", "legal_partnership_status_6a": "blocked", "national_identity_all_4a": "blocked", "ns_sec_10a": "blocked", "occupation_current_10a": "blocked", "religion_tb": "blocked", "residence_length_6b": "blocked", "resident_age_18b": {"count": [16609, 19850, 11852, 9746, 27834, 42923, 68101, 60220, 32774, 16756, 9763, 7340, 6170, 5471, 4529, 3331, 2815, 2508], "percent": [4.8, 5.7, 3.4, 2.8, 8.0, 12.3, 19.5, 17.3, 9.4, 4.8, 2.8, 2.1, 1.8, 1.6, 1.3, 1.0, 0.8, 0.7]}, "sex": {"count": [2078, 737], "percent": [73.8, 26.2]}, "transport_to_workplace_12a": "blocked", "workplace_travel_8a": "blocked", "total_pop": {"count": 2815, "percent": 0.0}}, "18": {"country_of_birth_3a": {"count": [20, 2488], "percent": [0.8, 99.2]}, "disability_3a": "blocked", "economic_activity_status_4a": "blocked", "english_proficiency": "blocked", "has_ever_worked": "blocked", "health_in_general": "blocked", "highest_qualification": "blocked", "hours_per_week_worked": "blocked", "is_carer_5a": "blocked", "legal_partnership_status_6a": "blocked", "national_identity_all_4a": "blocked", "ns_sec_10a": "blocked", "occupation_current_10a": "blocked", "religion_tb": "blocked", "residence_length_6b": "blocked", "resident_age_18b": {"count": [16609, 19850, 11852, 9746, 27834, 42923, 68101, 60220, 32774, 16756, 9763, 7340, 6170, 5471, 4529, 3331, 2815, 2508], "percent": [4.8, 5.7, 3.4, 2.8, 8.0, 12.3, 19.5, 17.3, 9.4, 4.8, 2.8, 2.1, 1.8, 1.6, 1.3, 1.0, 0.8, 0.7]}, "sex": {"count": [1929, 579], "percent": [76.9, 23.1]}, "transport_to_workplace_12a": "blocked", "workplace_travel_8a": "blocked", "total_pop": {"count": 2508, "percent": 0.0}}}