{"1": {"country_of_birth_3a": {"-8": 0, "1": 362, "2": 4523}, "disability_3a": {"-8": 0, "1": 80, "2": 4805}, "economic_activity_status_4a": {"-8": 4885, "1": 0, "2": 0, "3": 0}, "ethnic_group_tb_6a": "blocked", "has_ever_worked": {"-8": 4885, "1": 0, "2": 0, "3": 0}, "health_in_general": "blocked", "highest_qualification": {"-8": 4885, "0": 0, "1": 0, "2": 0, "3": 0, "4": 0, "5": 0, "6": 0}, "hours_per_week_worked": {"-8": 4885, "1": 0, "2": 0, "3": 0, "4": 0}, "is_carer_5a": "blocked", "legal_partnership_status_6a": {"-8": 4885, "1": 0, "2": 0, "3": 0, "4": 0, "5": 0}, "national_identity_all_4a": "blocked", "ns_sec_10a": {"-8": 4885, "1": 0, "2": 0, "3": 0, "4": 0, "5": 0, "6": 0, "7": 0, "8": 0, "9": 0}, "occupation_current_10a": "blocked", "religion_tb": "blocked", "residence_length_6b": "blocked", "resident_age_18b": {"1": 269, "2": 1742, "3": 2377, "4": 3267, "5": 5985, "6": 8740, "7": 10120, "8": 8179, "9": 5470, "10": 2991, "11": 1617, "12": 904, "13": 519, "14": 302, "15": 244, "16": 214, "17": 107, "18": 77}, "resident_age_23a": {"1": 0, "2": 269, "3": 936, "4": 806, "5": 2377, "6": 497, "7": 1152, "8": 1618, "9": 5985, "10": 8740, "11": 10120, "12": 8179, "13": 5470, "14": 2991, "15": 1617, "16": 904, "17": 519, "18": 69, "19": 233, "20": 244, "21": 214, "22": 107, "23": 77}, "sex": {"1": 2534, "2": 2351}, "transport_to_workplace_12a": "blocked", "workplace_travel_5a": "blocked"}, "2": {"country_of_birth_3a": {"-8": 0, "1": 189, "2": 47106}, "disability_3a": {"-8": 0, "1": 2227, "2": 45068}, "economic_activity_status_4a": {"-8": 0, "1": 32291, "2": 2799, "3": 12205}, "ethnic_group_tb_6a": "blocked", "has_ever_worked": {"-8": 32291, "1": 4299, "2": 4749, "3": 5956}, "health_in_general": "blocked", "highest_qualification": {"-8": 0, "0": 4242, "1": 1774, "2": 2455, "3": 1094, "4": 4706, "5": 30253, "6": 2770}, "hours_per_week_worked": {"-8": 15006, "1": 3393, "2": 4721, "3": 19793, "4": 4384}, "is_carer_5a": "blocked", "legal_partnership_status_6a": {"-8": 0, "1": 19591, "2": 24762, "3": 715, "4": 2084, "5": 144}, "national_identity_all_4a": "blocked", "ns_sec_10a": {"-8": 0, "1": 11873, "2": 8068, "3": 2780, "4": 6594, "5": 1347, "6": 2426, "7": 2594, "8": 2952, "9": 8661}, "occupation_current_10a": "blocked", "religion_tb": "blocked", "residence_length_6b": "blocked", "resident_age_18b": {"1": 269, "2": 1742, "3": 2377, "4": 3267, "5": 5985, "6": 8740, "7": 10120, "8": 8179, "9": 5470, "10": 2991, "11": 1617, "12": 904, "13": 519, "14": 302, "15": 244, "16": 214, "17": 107, "18": 77}, "resident_age_23a": {"1": 0, "2": 269, "3": 936, "4": 806, "5": 2377, "6": 497, "7": 1152, "8": 1618, "9": 5985, "10": 8740, "11": 10120, "12": 8179, "13": 5470, "14": 2991, "15": 1617, "16": 904, "17": 519, "18": 69, "19": 233, "20": 244, "21": 214, "22": 107, "23": 77}, "sex": {"1": 25640, "2": 21655}, "transport_to_workplace_12a": "blocked", "workplace_travel_5a": "blocked"}, "3": {"country_of_birth_3a": {"-8": 0, "1": 6, "2": 937}, "disability_3a": {"-8": 0, "1": 211, "2": 732}, "economic_activity_status_4a": {"-8": 0, "1": 159, "2": 8, "3": 776}, "ethnic_group_tb_6a": "blocked", "has_ever_worked": {"-8": 159, "1": 47, "2": 646, "3": 93}, "health_in_general": "blocked", "highest_qualification": {"-8": 0, "0": 115, "1": 36, "2": 46, "3": 79, "4": 102, "5": 504, "6": 61}, "hours_per_week_worked": {"-8": 784, "1": 53, "2": 48, "3": 45, "4": 12}, "is_carer_5a": "blocked", "legal_partnership_status_6a": {"-8": 0, "1": 58, "2": 592, "3": 15, "4": 119, "5": 159}, "national_identity_all_4a": "blocked", "ns_sec_10a": {"-8": 0, "1": 168, "2": 254, "3": 107, "4": 148, "5": 27, "6": 92, "7": 47, "8": 97, "9": 3}, "occupation_current_10a": "blocked", "religion_tb": "blocked", "residence_length_6b": "blocked", "resident_age_18b": {"1": 269, "2": 1742, "3": 2377, "4": 3267, "5": 5985, "6": 8740, "7": 10120, "8": 8179, "9": 5470, "10": 2991, "11": 1617, "12": 904, "13": 519, "14": 302, "15": 244, "16": 214, "17": 107, "18": 77}, "resident_age_23a": {"1": 0, "2": 269, "3": 936, "4": 806, "5": 2377, "6": 497, "7": 1152, "8": 1618, "9": 5985, "10": 8740, "11": 10120, "12": 8179, "13": 5470, "14": 2991, "15": 1617, "16": 904, "17": 519, "18": 69, "19": 233, "20": 244, "21": 214, "22": 107, "23": 77}, "sex": {"1": 604, "2": 339}, "transport_to_workplace_12a": "blocked", "workplace_travel_5a": "blocked"}}