{"1": {"country_of_birth_3a": {"-8": 0, "1": 170, "2": 2608}, "disability_3a": {"-8": 0, "1": 32, "2": 2746}, "economic_activity_status_4a": "blocked", "ethnic_group_tb_6a": "blocked", "has_ever_worked": "blocked", "health_in_general": "blocked", "highest_qualification": "blocked", "hours_per_week_worked": "blocked", "is_carer_5a": "blocked", "legal_partnership_status_6a": "blocked", "national_identity_all_4a": "blocked", "ns_sec_10a": "blocked", "occupation_current_10a": "blocked", "religion_tb": "blocked", "residence_length_6b": "blocked", "resident_age_18b": {"1": 169, "2": 1183, "3": 1259, "4": 1178, "5": 1369, "6": 2277, "7": 3451, "8": 2981, "9": 1774, "10": 965, "11": 512, "12": 279, "13": 106, "14": 71, "15": 46, "16": 23, "17": 11, "18": 9}, "resident_age_23a": {"1": 0, "2": 169, "3": 665, "4": 518, "5": 1259, "6": 167, "7": 381, "8": 630, "9": 1369, "10": 2277, "11": 3451, "12": 2981, "13": 1774, "14": 965, "15": 512, "16": 279, "17": 106, "18": 21, "19": 50, "20": 46, "21": 23, "22": 11, "23": 9}, "sex": {"1": 1362, "2": 1416}, "transport_to_workplace_12a": "blocked", "workplace_travel_5a": "blocked"}, "2": {"country_of_birth_3a": {"-8": 0, "1": 66, "2": 2315}, "disability_3a": {"-8": 0, "1": 115, "2": 2265}, "economic_activity_status_4a": "blocked", "ethnic_group_tb_6a": "blocked", "has_ever_worked": "blocked", "health_in_general": "blocked", "highest_qualification": "blocked", "hours_per_week_worked": "blocked", "is_carer_5a": "blocked", "legal_partnership_status_6a": "blocked", "national_identity_all_4a": "blocked", "ns_sec_10a": "blocked", "occupation_current_10a": "blocked", "religion_tb": "blocked", "residence_length_6b": "blocked", "resident_age_18b": {"1": 169, "2": 1183, "3": 1259, "4": 1178, "5": 1369, "6": 2277, "7": 3451, "8": 2981, "9": 1774, "10": 965, "11": 512, "12": 279, "13": 106, "14": 71, "15": 46, "16": 23, "17": 11, "18": 9}, "resident_age_23a": {"1": 0, "2": 169, "3": 665, "4": 518, "5": 1259, "6": 167, "7": 381, "8": 630, "9": 1369, "10": 2277, "11": 3451, "12": 2981, "13": 1774, "14": 965, "15": 512, "16": 279, "17": 106, "18": 21, "19": 50, "20": 46, "21": 23, "22": 11, "23": 9}, "sex": {"1": 1062, "2": 1318}, "transport_to_workplace_12a": "blocked", "workplace_travel_5a": "blocked"}, "3": {"country_of_birth_3a": {"-8": 0, "1": 46, "2": 5683}, "disability_3a": {"-8": 0, "1": 220, "2": 5509}, "economic_activity_status_4a": "blocked", "ethnic_group_tb_6a": "blocked", "has_ever_worked": "blocked", "health_in_general": "blocked", "highest_qualification": "blocked", "hours_per_week_worked": "blocked", "is_carer_5a": "blocked", "legal_partnership_status_6a": "blocked", "national_identity_all_4a": "blocked", "ns_sec_10a": "blocked", "occupation_current_10a": "blocked", "religion_tb": "blocked", "residence_length_6b": "blocked", "resident_age_18b": {"1": 169, "2": 1183, "3": 1259, "4": 1178, "5": 1369, "6": 2277, "7": 3451, "8": 2981, "9": 1774, "10": 965, "11": 512, "12": 279, "13": 106, "14": 71, "15": 46, "16": 23, "17": 11, "18": 9}, "resident_age_23a": {"1": 0, "2": 169, "3": 665, "4": 518, "5": 1259, "6": 167, "7": 381, "8": 630, "9": 1369, "10": 2277, "11": 3451, "12": 2981, "13": 1774, "14": 965, "15": 512, "16": 279, "17": 106, "18": 21, "19": 50, "20": 46, "21": 23, "22": 11, "23": 9}, "sex": {"1": 2563, "2": 3166}, "transport_to_workplace_12a": "blocked", "workplace_travel_5a": "blocked"}, "4": {"country_of_birth_3a": {"-8": 0, "1": 34, "2": 4721}, "disability_3a": {"-8": 0, "1": 258, "2": 4497}, "economic_activity_status_4a": "blocked", "ethnic_group_tb_6a": "blocked", "has_ever_worked": "blocked", "health_in_general": "blocked", "highest_qualification": "blocked", "hours_per_week_worked": "blocked", "is_carer_5a": "blocked", "legal_partnership_status_6a": "blocked", "national_identity_all_4a": "blocked", "ns_sec_10a": "blocked", "occupation_current_10a": "blocked", "religion_tb": "blocked", "residence_length_6b": "blocked", "resident_age_18b": {"1": 169, "2": 1183, "3": 1259, "4": 1178, "5": 1369, "6": 2277, "7": 3451, "8": 2981, "9": 1774, "10": 965, "11": 512, "12": 279, "13": 106, "14": 71, "15": 46, "16": 23, "17": 11, "18": 9}, "resident_age_23a": {"1": 0, "2": 169, "3": 665, "4": 518, "5": 1259, "6": 167, "7": 381, "8": 630, "9": 1369, "10": 2277, "11": 3451, "12": 2981, "13": 1774, "14": 965, "15": 512, "16": 279, "17": 106, "18": 21, "19": 50, "20": 46, "21": 23, "22": 11, "23": 9}, "sex": {"1": 1685, "2": 3070}, "transport_to_workplace_12a": "blocked", "workplace_travel_5a": "blocked"}, "5": {"country_of_birth_3a": {"-8": 0, "1": 5, "2": 1472}, "disability_3a": {"-8": 0, "1": 155, "2": 1322}, "economic_activity_status_4a": "blocked", "ethnic_group_tb_6a": "blocked", "has_ever_worked": "blocked", "health_in_general": "blocked", "highest_qualification": "blocked", "hours_per_week_worked": "blocked", "is_carer_5a": "blocked", "legal_partnership_status_6a": "blocked", "national_identity_all_4a": "blocked", "ns_sec_10a": "blocked", "occupation_current_10a": "blocked", "religion_tb": "blocked", "residence_length_6b": "blocked", "resident_age_18b": {"1": 169, "2": 1183, "3": 1259, "4": 1178, "5": 1369, "6": 2277, "7": 3451, "8": 2981, "9": 1774, "10": 965, "11": 512, "12": 279, "13": 106, "14": 71, "15": 46, "16": 23, "17": 11, "18": 9}, "resident_age_23a": {"1": 0, "2": 169, "3": 665, "4": 518, "5": 1259, "6": 167, "7": 381, "8": 630, "9": 1369, "10": 2277, "11": 3451, "12": 2981, "13": 1774, "14": 965, "15": 512, "16": 279, "17": 106, "18": 21, "19": 50, "20": 46, "21": 23, "22": 11, "23": 9}, "sex": {"1": 390, "2": 1088}, "transport_to_workplace_12a": "blocked", "workplace_travel_5a": "blocked"}, "6": {"country_of_birth_3a": {"-8": 0, "1": 0, "2": 385}, "disability_3a": {"-8": 0, "1": 61, "2": 323}, "economic_activity_status_4a": "blocked", "ethnic_group_tb_6a": "blocked", "has_ever_worked": "blocked", "health_in_general": "blocked", "highest_qualification": "blocked", "hours_per_week_worked": "blocked", "is_carer_5a": "blocked", "legal_partnership_status_6a": "blocked", "national_identity_all_4a": "blocked", "ns_sec_10a": "blocked", "occupation_current_10a": "blocked", "religion_tb": "blocked", "residence_length_6b": "blocked", "resident_age_18b": {"1": 169, "2": 1183, "3": 1259, "4": 1178, "5": 1369, "6": 2277, "7": 3451, "8": 2981, "9": 1774, "10": 965, "11": 512, "12": 279, "13": 106, "14": 71, "15": 46, "16": 23, "17": 11, "18": 9}, "resident_age_23a": {"1": 0, "2": 169, "3": 665, "4": 518, "5": 1259, "6": 167, "7": 381, "8": 630, "9": 1369, "10": 2277, "11": 3451, "12": 2981, "13": 1774, "14": 965, "15": 512, "16": 279, "17": 106, "18": 21, "19": 50, "20": 46, "21": 23, "22": 11, "23": 9}, "sex": {"1": 70, "2": 315}, "transport_to_workplace_12a": "blocked", "workplace_travel_5a": "blocked"}, "7": {"country_of_birth_3a": {"-8": 0, "1": 1, "2": 118}, "disability_3a": {"-8": 0, "1": 34, "2": 83}, "economic_activity_status_4a": "blocked", "ethnic_group_tb_6a": "blocked", "has_ever_worked": "blocked", "health_in_general": "blocked", "highest_qualification": "blocked", "hours_per_week_worked": "blocked", "is_carer_5a": "blocked", "legal_partnership_status_6a": "blocked", "national_identity_all_4a": "blocked", "ns_sec_10a": "blocked", "occupation_current_10a": "blocked", "religion_tb": "blocked", "residence_length_6b": "blocked", "resident_age_18b": {"1": 169, "2": 1183, "3": 1259, "4": 1178, "5": 1369, "6": 2277, "7": 3451, "8": 2981, "9": 1774, "10": 965, "11": 512, "12": 279, "13": 106, "14": 71, "15": 46, "16": 23, "17": 11, "18": 9}, "resident_age_23a": {"1": 0, "2": 169, "3": 665, "4": 518, "5": 1259, "6": 167, "7": 381, "8": 630, "9": 1369, "10": 2277, "11": 3451, "12": 2981, "13": 1774, "14": 965, "15": 512, "16": 279, "17": 106, "18": 21, "19": 50, "20": 46, "21": 23, "22": 11, "23": 9}, "sex": {"1": 28, "2": 89}, "transport_to_workplace_12a": "blocked", "workplace_travel_5a": "blocked"}, "8": {"country_of_birth_3a": {"-8": 0, "1": 1, "2": 40}, "disability_3a": {"-8": 0, "1": 17, "2": 24}, "economic_activity_status_4a": "blocked", "ethnic_group_tb_6a": "blocked", "has_ever_worked": "blocked", "health_in_general": "blocked", "highest_qualification": "blocked", "hours_per_week_worked": "blocked", "is_carer_5a": "blocked", "legal_partnership_status_6a": "blocked", "national_identity_all_4a": "blocked", "ns_sec_10a": "blocked", "occupation_current_10a": "blocked", "religion_tb": "blocked", "residence_length_6b": "blocked", "resident_age_18b": {"1": 169, "2": 1183, "3": 1259, "4": 1178, "5": 1369, "6": 2277, "7": 3451, "8": 2981, "9": 1774, "10": 965, "11": 512, "12": 279, "13": 106, "14": 71, "15": 46, "16": 23, "17": 11, "18": 9}, "resident_age_23a": {"1": 0, "2": 169, "3": 665, "4": 518, "5": 1259, "6": 167, "7": 381, "8": 630, "9": 1369, "10": 2277, "11": 3451, "12": 2981, "13": 1774, "14": 965, "15": 512, "16": 279, "17": 106, "18": 21, "19": 50, "20": 46, "21": 23, "22": 11, "23": 9}, "sex": {"1": 9, "2": 32}, "transport_to_workplace_12a": "blocked", "workplace_travel_5a": "blocked"}}