{"1": {"disability_3a": {"count": [30, 1603], "percent": [1.8, 98.2]}, "economic_activity_status_4a": "blocked", "english_proficiency": "blocked", "has_ever_worked": "blocked", "health_in_general": "blocked", "highest_qualification": "blocked", "hours_per_week_worked": "blocked", "is_carer_5a": "blocked", "legal_partnership_status_6a": "blocked", "national_identity_all_4a": "blocked", "ns_sec_10a": "blocked", "occupation_current_10a": "blocked", "passports_all_4a": "blocked", "religion_tb": "blocked", "residence_length_6b": "blocked", "resident_age_18b": {"count": [1633, 3800, 4189, 3969, 4475, 3466, 3101, 2634, 2058, 1842, 1721, 1742, 1892, 1828, 1620, 1244, 925, 835], "percent": [3.8, 8.8, 9.7, 9.2, 10.4, 8.1, 7.2, 6.1, 4.8, 4.3, 4.0, 4.1, 4.4, 4.3, 3.8, 2.9, 2.2, 1.9]}, "sex": {"count": [773, 861], "percent": [47.3, 52.7]}, "transport_to_workplace_12a": "blocked", "workplace_travel_8a": "blocked", "total_pop": {"count": 1633, "percent": 0.0}}, "2": {"disability_3a": {"count": [102, 3698], "percent": [2.7, 97.3]}, "economic_activity_status_4a": "blocked", "english_proficiency": "blocked", "has_ever_worked": "blocked", "health_in_general": "blocked", "highest_qualification": "blocked", "hours_per_week_worked": "blocked", "is_carer_5a": "blocked", "legal_partnership_status_6a": "blocked", "national_identity_all_4a": "blocked", "ns_sec_10a": "blocked", "occupation_current_10a": "blocked", "passports_all_4a": "blocked", "religion_tb": "blocked", "residence_length_6b": "blocked", "resident_age_18b": {"count": [1633, 3800, 4189, 3969, 4475, 3466, 3101, 2634, 2058, 1842, 1721, 1742, 1892, 1828, 1620, 1244, 925, 835], "percent": [3.8, 8.8, 9.7, 9.2, 10.4, 8.1, 7.2, 6.1, 4.8, 4.3, 4.0, 4.1, 4.4, 4.3, 3.8, 2.9, 2.2, 1.9]}, "sex": {"count": [1886, 1914], "percent": [49.6, 50.4]}, "transport_to_workplace_12a": "blocked", "workplace_travel_8a": "blocked", "total_pop": {"count": 3800, "percent": 0.0}}, "3": {"disability_3a": {"count": [168, 4021], "percent": [4.0, 96.0]}, "economic_activity_status_4a": "blocked", "english_proficiency": "blocked", "has_ever_worked": "blocked", "health_in_general": "blocked", "highest_qualification": "blocked", "hours_per_week_worked": "blocked", "is_carer_5a": "blocked", "legal_partnership_status_6a": "blocked", "national_identity_all_4a": "blocked", "ns_sec_10a": "blocked", "occupation_current_10a": "blocked", "passports_all_4a": "blocked", "religion_tb": "blocked", "residence_length_6b": "blocked", "resident_age_18b": {"count": [1633, 3800, 4189, 3969, 4475, 3466, 3101, 2634, 2058, 1842, 1721, 1742, 1892, 1828, 1620, 1244, 925, 835], "percent": [3.8, 8.8, 9.7, 9.2, 10.4, 8.1, 7.2, 6.1, 4.8, 4.3, 4.0, 4.1, 4.4, 4.3, 3.8, 2.9, 2.2, 1.9]}, "sex": {"count": [2025, 2163], "percent": [48.4, 51.6]}, "transport_to_workplace_12a": "blocked", "workplace_travel_8a": "blocked", "total_pop": {"count": 4189, "percent": 0.0}}, "4": {"disability_3a": {"count": [294, 3675], "percent": [7.4, 92.6]}, "economic_activity_status_4a": "blocked", "english_proficiency": "blocked", "has_ever_worked": "blocked", "health_in_general": "blocked", "highest_qualification": "blocked", "hours_per_week_worked": "blocked", "is_carer_5a": "blocked", "legal_partnership_status_6a": "blocked", "national_identity_all_4a": "blocked", "ns_sec_10a": "blocked", "occupation_current_10a": "blocked", "passports_all_4a": "blocked", "religion_tb": "blocked", "residence_length_6b": "blocked", "resident_age_18b": {"count": [1633, 3800, 4189, 3969, 4475, 3466, 3101, 2634, 2058, 1842, 1721, 1742, 1892, 1828, 1620, 1244, 925, 835], "percent": [3.8, 8.8, 9.7, 9.2, 10.4, 8.1, 7.2, 6.1, 4.8, 4.3, 4.0, 4.1, 4.4, 4.3, 3.8, 2.9, 2.2, 1.9]}, "sex": {"count": [2008, 1961], "percent": [50.6, 49.4]}, "transport_to_workplace_12a": "blocked", "workplace_travel_8a": "blocked", "total_pop": {"count": 3969, "percent": 0.0}}, "5": {"disability_3a": {"count": [504, 3974], "percent": [11.3, 88.7]}, "economic_activity_status_4a": "blocked", "english_proficiency": "blocked", "has_ever_worked": "blocked", "health_in_general": "blocked", "highest_qualification": "blocked", "hours_per_week_worked": "blocked", "is_carer_5a": "blocked", "legal_partnership_status_6a": "blocked", "national_identity_all_4a": "blocked", "ns_sec_10a": "blocked", "occupation_current_10a": "blocked", "passports_all_4a": "blocked", "religion_tb": "blocked", "residence_length_6b": "blocked", "resident_age_18b": {"count": [1633, 3800, 4189, 3969, 4475, 3466, 3101, 2634, 2058, 1842, 1721, 1742, 1892, 1828, 1620, 1244, 925, 835], "percent": [3.8, 8.8, 9.7, 9.2, 10.4, 8.1, 7.2, 6.1, 4.8, 4.3, 4.0, 4.1, 4.4, 4.3, 3.8, 2.9, 2.2, 1.9]}, "sex": {"count": [2327, 2148], "percent": [52.0, 48.0]}, "transport_to_workplace_12a": "blocked", "workplace_travel_8a": "blocked", "total_pop": {"count": 4475, "percent": 0.0}}, "6": {"disability_3a": {"count": [298, 3168], "percent": [8.6, 91.4]}, "economic_activity_status_4a": "blocked", "english_proficiency": "blocked", "has_ever_worked": "blocked", "health_in_general": "blocked", "highest_qualification": "blocked", "hours_per_week_worked": "blocked", "is_carer_5a": "blocked", "legal_partnership_status_6a": "blocked", "national_identity_all_4a": "blocked", "ns_sec_10a": "blocked", "occupation_current_10a": "blocked", "passports_all_4a": "blocked", "religion_tb": "blocked", "residence_length_6b": "blocked", "resident_age_18b": {"count": [1633, 3800, 4189, 3969, 4475, 3466, 3101, 2634, 2058, 1842, 1721, 1742, 1892, 1828, 1620, 1244, 925, 835], "percent": [3.8, 8.8, 9.7, 9.2, 10.4, 8.1, 7.2, 6.1, 4.8, 4.3, 4.0, 4.1, 4.4, 4.3, 3.8, 2.9, 2.2, 1.9]}, "sex": {"count": [1802, 1663], "percent": [52.0, 48.0]}, "transport_to_workplace_12a": "blocked", "workplace_travel_8a": "blocked", "total_pop": {"count": 3466, "percent": 0.0}}, "7": {"disability_3a": {"count": [248, 2853], "percent": [8.0, 92.0]}, "economic_activity_status_4a": "blocked", "english_proficiency": "blocked", "has_ever_worked": "blocked", "health_in_general": "blocked", "highest_qualification": "blocked", "hours_per_week_worked": "blocked", "is_carer_5a": "blocked", "legal_partnership_status_6a": "blocked", "national_identity_all_4a": "blocked", "ns_sec_10a": "blocked", "occupation_current_10a": "blocked", "passports_all_4a": "blocked", "religion_tb": "blocked", "residence_length_6b": "blocked", "resident_age_18b": {"count": [1633, 3800, 4189, 3969, 4475, 3466, 3101, 2634, 2058, 1842, 1721, 1742, 1892, 1828, 1620, 1244, 925, 835], "percent": [3.8, 8.8, 9.7, 9.2, 10.4, 8.1, 7.2, 6.1, 4.8, 4.3, 4.0, 4.1, 4.4, 4.3, 3.8, 2.9, 2.2, 1.9]}, "sex": {"count": [1517, 1584], "percent": [48.9, 51.1]}, "transport_to_workplace_12a": "blocked", "workplace_travel_8a": "blocked", "total_pop": {"count": 3101, "percent": 0.0}}, "8": {"disability_3a": {"count": [225, 2409], "percent": [8.5, 91.5]}, "economic_activity_status_4a": "blocked", "english_proficiency": "blocked", "has_ever_worked": "blocked", "health_in_general": "blocked", "highest_qualification": "blocked", "hours_per_week_worked": "blocked", "is_carer_5a": "blocked", "legal_partnership_status_6a": "blocked", "national_identity_all_4a": "blocked", "ns_sec_10a": "blocked", "occupation_current_10a": "blocked", "passports_all_4a": "blocked", "religion_tb": "blocked", "residence_length_6b": "blocked", "resident_age_18b": {"count": [1633, 3800, 4189, 3969, 4475, 3466, 3101, 2634, 2058, 1842, 1721, 1742, 1892, 1828, 1620, 1244, 925, 835], "percent": [3.8, 8.8, 9.7, 9.2, 10.4, 8.1, 7.2, 6.1, 4.8, 4.3, 4.0, 4.1, 4.4, 4.3, 3.8, 2.9, 2.2, 1.9]}, "sex": {"count": [1335, 1299], "percent": [50.7, 49.3]}, "transport_to_workplace_12a": "blocked", "workplace_travel_8a": "blocked", "total_pop": {"count": 2634, "percent": 0.0}}, "9": {"disability_3a": {"count": [238, 1821], "percent": [11.6, 88.4]}, "economic_activity_status_4a": "blocked", "english_proficiency": "blocked", "has_ever_worked": "blocked", "health_in_general": "blocked", "highest_qualification": "blocked", "hours_per_week_worked": "blocked", "is_carer_5a": "blocked", "legal_partnership_status_6a": "blocked", "national_identity_all_4a": "blocked", "ns_sec_10a": "blocked", "occupation_current_10a": "blocked", "passports_all_4a": "blocked", "religion_tb": "blocked", "residence_length_6b": "blocked", "resident_age_18b": {"count": [1633, 3800, 4189, 3969, 4475, 3466, 3101, 2634, 2058, 1842, 1721, 1742, 1892, 1828, 1620, 1244, 925, 835], "percent": [3.8, 8.8, 9.7, 9.2, 10.4, 8.1, 7.2, 6.1, 4.8, 4.3, 4.0, 4.1, 4.4, 4.3, 3.8, 2.9, 2.2, 1.9]}, "sex": {"count": [997, 1061], "percent": [48.4, 51.6]}, "transport_to_workplace_12a": "blocked", "workplace_travel_8a": "blocked", "total_pop": {"count": 2058, "percent": 0.0}}, "10": {"disability_3a": {"count": [251, 1591], "percent": [13.6, 86.4]}, "economic_activity_status_4a": "blocked", "english_proficiency": "blocked", "has_ever_worked": "blocked", "health_in_general": "blocked", "highest_qualification": "blocked", "hours_per_week_worked": "blocked", "is_carer_5a": "blocked", "legal_partnership_status_6a": "blocked", "national_identity_all_4a": "blocked", "ns_sec_10a": "blocked", "occupation_current_10a": "blocked", "passports_all_4a": "blocked", "religion_tb": "blocked", "residence_length_6b": "blocked", "resident_age_18b": {"count": [1633, 3800, 4189, 3969, 4475, 3466, 3101, 2634, 2058, 1842, 1721, 1742, 1892, 1828, 1620, 1244, 925, 835], "percent": [3.8, 8.8, 9.7, 9.2, 10.4, 8.1, 7.2, 6.1, 4.8, 4.3, 4.0, 4.1, 4.4, 4.3, 3.8, 2.9, 2.2, 1.9]}, "sex": {"count": [917, 925], "percent": [49.8, 50.2]}, "transport_to_workplace_12a": "blocked", "workplace_travel_8a": "blocked", "total_pop": {"count": 1842, "percent": 0.0}}, "11": {"disability_3a": {"count": [265, 1456], "percent": [15.4, 84.6]}, "economic_activity_status_4a": "blocked", "english_proficiency": "blocked", "has_ever_worked": "blocked", "health_in_general": "blocked", "highest_qualification": "blocked", "hours_per_week_worked": "blocked", "is_carer_5a": "blocked", "legal_partnership_status_6a": "blocked", "national_identity_all_4a": "blocked", "ns_sec_10a": "blocked", "occupation_current_10a": "blocked", "passports_all_4a": "blocked", "religion_tb": "blocked", "residence_length_6b": "blocked", "resident_age_18b": {"count": [1633, 3800, 4189, 3969, 4475, 3466, 3101, 2634, 2058, 1842, 1721, 1742, 1892, 1828, 1620, 1244, 925, 835], "percent": [3.8, 8.8, 9.7, 9.2, 10.4, 8.1, 7.2, 6.1, 4.8, 4.3, 4.0, 4.1, 4.4, 4.3, 3.8, 2.9, 2.2, 1.9]}, "sex": {"count": [873, 848], "percent": [50.7, 49.3]}, "transport_to_workplace_12a": "blocked", "workplace_travel_8a": "blocked", "total_pop": {"count": 1721, "percent": 0.0}}, "12": {"disability_3a": {"count": [309, 1433], "percent": [17.7, 82.3]}, "economic_activity_status_4a": "blocked", "english_proficiency": "blocked", "has_ever_worked": "blocked", "health_in_general": "blocked", "highest_qualification": "blocked", "hours_per_week_worked": "blocked", "is_carer_5a": "blocked", "legal_partnership_status_6a": "blocked", "national_identity_all_4a": "blocked", "ns_sec_10a": "blocked", "occupation_current_10a": "blocked", "passports_all_4a": "blocked", "religion_tb": "blocked", "residence_length_6b": "blocked", "resident_age_18b": {"count": [1633, 3800, 4189, 3969, 4475, 3466, 3101, 2634, 2058, 1842, 1721, 1742, 1892, 1828, 1620, 1244, 925, 835], "percent": [3.8, 8.8, 9.7, 9.2, 10.4, 8.1, 7.2, 6.1, 4.8, 4.3, 4.0, 4.1, 4.4, 4.3, 3.8, 2.9, 2.2, 1.9]}, "sex": {"count": [965, 777], "percent": [55.4, 44.6]}, "transport_to_workplace_12a": "blocked", "workplace_travel_8a": "blocked", "total_pop": {"count": 1742, "percent": 0.0}}, "13": {"disability_3a": {"count": [397, 1495], "percent": [21.0, 79.0]}, "economic_activity_status_4a": "blocked", "english_proficiency": "blocked", "has_ever_worked": "blocked", "health_in_general": "blocked", "highest_qualification": "blocked", "hours_per_week_worked": "blocked", "is_carer_5a": "blocked", "legal_partnership_status_6a": "blocked", "national_identity_all_4a": "blocked", "ns_sec_10a": "blocked", "occupation_current_10a": "blocked", "passports_all_4a": "blocked", "religion_tb": "blocked", "residence_length_6b": "blocked", "resident_age_18b": {"count": [1633, 3800, 4189, 3969, 4475, 3466, 3101, 2634, 2058, 1842, 1721, 1742, 1892, 1828, 1620, 1244, 925, 835], "percent": [3.8, 8.8, 9.7, 9.2, 10.4, 8.1, 7.2, 6.1, 4.8, 4.3, 4.0, 4.1, 4.4, 4.3, 3.8, 2.9, 2.2, 1.9]}, "sex": {"count": [1015, 879], "percent": [53.6, 46.4]}, "transport_to_workplace_12a": "blocked", "workplace_travel_8a": "blocked", "total_pop": {"count": 1892, "percent": 0.0}}, "14": {"disability_3a": {"count": [446, 1382], "percent": [24.4, 75.6]}, "economic_activity_status_4a": "blocked", "english_proficiency": "blocked", "has_ever_worked": "blocked", "health_in_general": "blocked", "highest_qualification": "blocked", "hours_per_week_worked": "blocked", "is_carer_5a": "blocked", "legal_partnership_status_6a": "blocked", "national_identity_all_4a": "blocked", "ns_sec_10a": "blocked", "occupation_current_10a": "blocked", "passports_all_4a": "blocked", "religion_tb": "blocked", "residence_length_6b": "blocked", "resident_age_18b": {"count": [1633, 3800, 4189, 3969, 4475, 3466, 3101, 2634, 2058, 1842, 1721, 1742, 1892, 1828, 1620, 1244, 925, 835], "percent": [3.8, 8.8, 9.7, 9.2, 10.4, 8.1, 7.2, 6.1, 4.8, 4.3, 4.0, 4.1, 4.4, 4.3, 3.8, 2.9, 2.2, 1.9]}, "sex": {"count": [974, 854], "percent": [53.3, 46.7]}, "transport_to_workplace_12a": "blocked", "workplace_travel_8a": "blocked", "total_pop": {"count": 1828, "percent": 0.0}}, "15": {"disability_3a": {"count": [390, 1230], "percent": [24.1, 75.9]}, "economic_activity_status_4a": "blocked", "english_proficiency": "blocked", "has_ever_worked": "blocked", "health_in_general": "blocked", "highest_qualification": "blocked", "hours_per_week_worked": "blocked", "is_carer_5a": "blocked", "legal_partnership_status_6a": "blocked", "national_identity_all_4a": "blocked", "ns_sec_10a": "blocked", "occupation_current_10a": "blocked", "passports_all_4a": "blocked", "religion_tb": "blocked", "residence_length_6b": "blocked", "resident_age_18b": {"count": [1633, 3800, 4189, 3969, 4475, 3466, 3101, 2634, 2058, 1842, 1721, 1742, 1892, 1828, 1620, 1244, 925, 835], "percent": [3.8, 8.8, 9.7, 9.2, 10.4, 8.1, 7.2, 6.1, 4.8, 4.3, 4.0, 4.1, 4.4, 4.3, 3.8, 2.9, 2.2, 1.9]}, "sex": {"count": [881, 739], "percent": [54.4, 45.6]}, "transport_to_workplace_12a": "blocked", "workplace_travel_8a": "blocked", "total_pop": {"count": 1620, "percent": 0.0}}, "16": {"disability_3a": {"count": [412, 831], "percent": [33.1, 66.9]}, "economic_activity_status_4a": "blocked", "english_proficiency": "blocked", "has_ever_worked": "blocked", "health_in_general": "blocked", "highest_qualification": "blocked", "hours_per_week_worked": "blocked", "is_carer_5a": "blocked", "legal_partnership_status_6a": "blocked", "national_identity_all_4a": "blocked", "ns_sec_10a": "blocked", "occupation_current_10a": "blocked", "passports_all_4a": "blocked", "religion_tb": "blocked", "residence_length_6b": "blocked", "resident_age_18b": {"count": [1633, 3800, 4189, 3969, 4475, 3466, 3101, 2634, 2058, 1842, 1721, 1742, 1892, 1828, 1620, 1244, 925, 835], "percent": [3.8, 8.8, 9.7, 9.2, 10.4, 8.1, 7.2, 6.1, 4.8, 4.3, 4.0, 4.1, 4.4, 4.3, 3.8, 2.9, 2.2, 1.9]}, "sex": {"count": [645, 599], "percent": [51.8, 48.2]}, "transport_to_workplace_12a": "blocked", "workplace_travel_8a": "blocked", "total_pop": {"count": 1244, "percent": 0.0}}, "17": {"disability_3a": {"count": [369, 556], "percent": [39.9, 60.1]}, "economic_activity_status_4a": "blocked", "english_proficiency": "blocked", "has_ever_worked": "blocked", "health_in_general": "blocked", "highest_qualification": "blocked", "hours_per_week_worked": "blocked", "is_carer_5a": "blocked", "legal_partnership_status_6a": "blocked", "national_identity_all_4a": "blocked", "ns_sec_10a": "blocked", "occupation_current_10a": "blocked", "passports_all_4a": "blocked", "religion_tb": "blocked", "residence_length_6b": "blocked", "resident_age_18b": {"count": [1633, 3800, 4189, 3969, 4475, 3466, 3101, 2634, 2058, 1842, 1721, 1742, 1892, 1828, 1620, 1244, 925, 835], "percent": [3.8, 8.8, 9.7, 9.2, 10.4, 8.1, 7.2, 6.1, 4.8, 4.3, 4.0, 4.1, 4.4, 4.3, 3.8, 2.9, 2.2, 1.9]}, "sex": {"count": [452, 473], "percent": [48.9, 51.1]}, "transport_to_workplace_12a": "blocked", "workplace_travel_8a": "blocked", "total_pop": {"count": 925, "percent": 0.0}}, "18": {"disability_3a": {"count": [447, 386], "percent": [53.7, 46.3]}, "economic_activity_status_4a": "blocked", "english_proficiency": "blocked", "has_ever_worked": "blocked", "health_in_general": "blocked", "highest_qualification": "blocked", "hours_per_week_worked": "blocked", "is_carer_5a": "blocked", "legal_partnership_status_6a": "blocked", "national_identity_all_4a": "blocked", "ns_sec_10a": "blocked", "occupation_current_10a": "blocked", "passports_all_4a": "blocked", "religion_tb": "blocked", "residence_length_6b": "blocked", "resident_age_18b": {"count": [1633, 3800, 4189, 3969, 4475, 3466, 3101, 2634, 2058, 1842, 1721, 1742, 1892, 1828, 1620, 1244, 925, 835], "percent": [3.8, 8.8, 9.7, 9.2, 10.4, 8.1, 7.2, 6.1, 4.8, 4.3, 4.0, 4.1, 4.4, 4.3, 3.8, 2.9, 2.2, 1.9]}, "sex": {"count": [547, 286], "percent": [65.7, 34.3]}, "transport_to_workplace_12a": "blocked", "workplace_travel_8a": "blocked", "total_pop": {"count": 835, "percent": 0.0}}}